wwshc/__init__.py
wwshc/wwsels.py
wwshc/wwserr.py
wwshc/wwsevent.py
wwshc/wwsopt.py
wwshc-0.0.11.dist-info/LICENSE.txt
wwshc-0.0.11.dist-info/METADATA
wwshc-0.0.11.dist-info/WHEEL
wwshc-0.0.11.dist-info/top_level.txt
wwshc-0.0.11.dist-info/RECORD
