Metadata-Version: 2.1
Name: wwshc
Version: 0.0.11
Summary: UNKNOWN
Home-page: https://wwshc.jojojux.de/
Author: JoJoJux
Author-email: wwshc@jojojux.de
License: UNKNOWN
Project-URL: Bug Tracker, https://wwshc.jojoux.de/bugs
Platform: UNKNOWN
Requires-Python: >=3.7, <4
License-File: LICENSE.txt
